LICENSE
MANIFEST.in
README.rst
setup.cfg
setup.py
solstice/__init__.py
solstice/core/__init__.py
solstice/core/__logging__.ini
solstice/core/__version__.py
solstice/core/asset.py
solstice/core/assetfile.py
solstice/core/assetsviewer.py
solstice/core/defines.py
solstice/core/node.py
solstice/core/project.py
solstice/core/shelf.py
solstice/core/tray.py
solstice/resources/icons/color/alembic.png
solstice/resources/icons/color/animation.png
solstice/resources/icons/color/background_element.png
solstice/resources/icons/color/background_elements.png
solstice/resources/icons/color/character.png
solstice/resources/icons/color/fx.png
solstice/resources/icons/color/groom.png
solstice/resources/icons/color/manual.png
solstice/resources/icons/color/message.png
solstice/resources/icons/color/prop.png
solstice/resources/icons/color/rig.png
solstice/resources/icons/lightrigs/daylight.png
solstice/resources/icons/lightrigs/neutral contrast.png
solstice/resources/icons/lightrigs/set props.png
solstice/resources/icons/logos/artella.png
solstice/resources/icons/logos/solstice.png
solstice/resources/icons/shelf/aTools.png
solstice/resources/icons/shelf/abcexporter.png
solstice/resources/icons/shelf/alembic.png
solstice/resources/icons/shelf/artella.png
solstice/resources/icons/shelf/artella_upload.png
solstice/resources/icons/shelf/artellamanager.png
solstice/resources/icons/shelf/assetviewer.png
solstice/resources/icons/shelf/changelog.png
solstice/resources/icons/shelf/empty_icon.png
solstice/resources/icons/shelf/importer.png
solstice/resources/icons/shelf/lightrigs.png
solstice/resources/icons/shelf/lock_file.png
solstice/resources/icons/shelf/ml_convertRotationOrder.png
solstice/resources/icons/shelf/outline.png
solstice/resources/icons/shelf/picker.png
solstice/resources/icons/shelf/pipeline.png
solstice/resources/icons/shelf/project.png
solstice/resources/icons/shelf/refreshvl.png
solstice/resources/icons/shelf/sanityCheck.png
solstice/resources/icons/shelf/scatter.png
solstice_core.egg-info/PKG-INFO
solstice_core.egg-info/SOURCES.txt
solstice_core.egg-info/dependency_links.txt
solstice_core.egg-info/not-zip-safe
solstice_core.egg-info/requires.txt
solstice_core.egg-info/top_level.txt
